{
  "hyperparameters": {
    "architecture": "convffnn",
    "batch_size": 100,
    "clipping_threshold": 0.0,
    "dataset_name": "mnist",
    "epochs": 1,
    "initialization_scale": "\\sqrt{\frac{6}{n+m}}",
    "lr": 0.9,
    "momentum": 0.0,
    "mu": 0.0,
    "seed": 19,
    "sgdtype": "implicit",
    "data_type": "classification"
  },
  "results": {
    "train": {
      "average_loss": [
        0.3054922100280722
      ],
      "average_accuracy": [
        91.52
      ]
    },
    "test": {
      "average_loss": [
        0.29103754468262194
      ],
      "average_accuracy": [
        91.92
      ]
    },
    "runtime": 54.50033926963806
  }
}