{
  "hyperparameters": {
    "architecture": "convffnn",
    "batch_size": 100,
    "clipping_threshold": 0.0,
    "dataset_name": "mnist",
    "epochs": 1,
    "initialization_scale": "\\sqrt{\frac{6}{n+m}}",
    "lr": 1.7,
    "momentum": 0.0,
    "mu": 0.0,
    "seed": 8,
    "sgdtype": "explicit",
    "data_type": "classification"
  },
  "results": {
    "train": {
      "average_loss": [
        2.1983763949076334
      ],
      "average_accuracy": [
        15.248333333333333
      ]
    },
    "test": {
      "average_loss": [
        2.1999773597717285
      ],
      "average_accuracy": [
        15.13
      ]
    },
    "runtime": 15.468043088912964
  }
}