{
  "hyperparameters": {
    "architecture": "classification",
    "batch_size": 100,
    "clipping_threshold": 0.0,
    "dataset_name": "letter_classification",
    "epochs": 10,
    "initialization_scale": "\\sqrt{\frac{6}{n+m}}",
    "inner_ISGD_iterations": 0,
    "intra_epoch": false,
    "lr": 10.0,
    "momentum": 0.0,
    "mu": 0.0,
    "nodes": 50,
    "seed": 1,
    "sgdtype": "explicit",
    "data_type": "classification"
  },
  "results": {
    "train": {
      "average_loss": [
        13.091936951875686,
        11.66187697649002,
        7.523374375700951,
        7.877825483679771,
        7.670391491055488,
        7.9551857024431225,
        7.282234156131745,
        7.066934409737587,
        7.573850998282433,
        5.984589149057865
      ],
      "average_accuracy": [
        10.29375,
        12.4625,
        17.19375,
        15.28125,
        13.8,
        13.14375,
        17.5125,
        15.20625,
        17.26875,
        18.0375
      ]
    },
    "test": {
      "average_loss": [
        13.36852810382843,
        11.673639059066772,
        7.516658806800843,
        7.893460822105408,
        7.836252117156983,
        8.22465831041336,
        7.280390202999115,
        6.952140533924103,
        7.587620103359223,
        6.038218700885773
      ],
      "average_accuracy": [
        10.375,
        11.75,
        16.525,
        15.925,
        13.9,
        13.2,
        17.6,
        15.7,
        17.0,
        17.4
      ]
    },
    "average_loss_intra_epoch": [
      5.984589149057865
    ],
    "average_accuracy_intra_epoch": [
      18.0375
    ],
    "runtime": 20.251254320144653
  }
}