{
  "hyperparameters": {
    "architecture": "classification",
    "batch_size": 100,
    "clipping_threshold": 0.0,
    "dataset_name": "chess-krvkp_classification",
    "epochs": 10,
    "initialization_scale": "\\sqrt{\frac{6}{n+m}}",
    "inner_ISGD_iterations": 0,
    "intra_epoch": false,
    "lr": 0.01,
    "momentum": 0.0,
    "mu": 0.0,
    "nodes": 50,
    "seed": 1,
    "sgdtype": "explicit",
    "data_type": "classification"
  },
  "results": {
    "train": {
      "average_loss": [
        0.6940524669793936,
        0.6927591631045709,
        0.6915447230522449,
        0.6903669123466198,
        0.6891908370531522,
        0.6879860391983619,
        0.6867235280000247,
        0.6853741590793316,
        0.683906729404743,
        0.6822861845676715
      ],
      "average_accuracy": [
        47.02660406885759,
        54.02973395931142,
        56.33802816901409,
        56.18153364632238,
        55.82942097026604,
        55.94679186228482,
        56.220657276995304,
        56.72926447574335,
        57.27699530516432,
        57.90297339593114
      ]
    },
    "test": {
      "average_loss": [
        0.6945951155253819,
        0.6932130541120257,
        0.6919337936810085,
        0.6907109873635429,
        0.6895069139344352,
        0.6882886205400739,
        0.687025419303349,
        0.6856866819517953,
        0.6842402390071324,
        0.682650761944907
      ],
      "average_accuracy": [
        44.6875,
        51.875,
        54.6875,
        55.78125,
        55.78125,
        55.46875,
        55.78125,
        56.5625,
        57.03125,
        57.8125
      ]
    },
    "average_loss_intra_epoch": [
      0.6822861845676715
    ],
    "average_accuracy_intra_epoch": [
      57.90297339593114
    ],
    "runtime": 6.394017934799194
  }
}