{
  "hyperparameters": {
    "architecture": "music",
    "batch_size": 100,
    "clipping_threshold": 0.0,
    "dataset_name": "JSB Chorales",
    "epochs": 5,
    "initialization_scale": "\\sqrt{\frac{6}{n+m}}",
    "inner_ISGD_iterations": 0,
    "intra_epoch": false,
    "lr": 200.0,
    "momentum": 0.0,
    "mu": 0.0,
    "nodes": 300,
    "seed": 2,
    "sgdtype": "implicit",
    "data_type": "sequential_many"
  },
  "results": {
    "train": {
      "average_loss": [
        0.0030907170729372064,
        0.002422991560901186,
        0.0019324542694027622,
        0.0016291345376623022,
        0.004021634078303995
      ],
      "average_accuracy": [
        0,
        0,
        0,
        0,
        0
      ]
    },
    "test": {
      "average_loss": [
        0.0031261624342780077,
        0.0024956803770385103,
        0.002015234127280895,
        0.001709001102143076,
        0.0031223884143400937
      ],
      "average_accuracy": [
        0,
        0,
        0,
        0,
        0
      ]
    },
    "average_loss_intra_epoch": [
      0.004021634078303995
    ],
    "average_accuracy_intra_epoch": [
      0
    ],
    "runtime": 513.6000542640686
  }
}