{
  "hyperparameters": {
    "architecture": "convffnn",
    "batch_size": 100,
    "clipping_threshold": 0.0,
    "dataset_name": "mnist",
    "epochs": 1,
    "initialization_scale": "\\sqrt{\frac{6}{n+m}}",
    "lr": 0.5,
    "momentum": 0.0,
    "mu": 0.0,
    "seed": 11,
    "sgdtype": "explicit",
    "data_type": "classification"
  },
  "results": {
    "train": {
      "average_loss": [
        0.12176777849439531
      ],
      "average_accuracy": [
        96.39
      ]
    },
    "test": {
      "average_loss": [
        0.10932170491665602
      ],
      "average_accuracy": [
        96.72
      ]
    },
    "runtime": 13.896333694458008
  }
}